nacos_sdk/__init__.py
nacos_sdk/adapters.py
nacos_sdk/client.py
nacos_sdk/parsers.py
nacos_sdk/py.typed
ola_ra_nacos_sdk-0.2.0.dist-info/METADATA
ola_ra_nacos_sdk-0.2.0.dist-info/WHEEL
ola_ra_nacos_sdk-0.2.0.dist-info/top_level.txt
ola_ra_nacos_sdk-0.2.0.dist-info/RECORD
