Metadata-Version: 2.4
Name: ola-ra-nacos-sdk
Version: 0.2.0
Summary: 一个轻量级的Python SDK，用于监听Nacos配置中心的配置变更
Home-page: 
Author: RA Team
Author-email: 
License: MIT
Project-URL: Homepage, https://github.com/your-org/ra-common-sdk
Project-URL: Documentation, https://github.com/your-org/ra-common-sdk#readme
Project-URL: Repository, https://github.com/your-org/ra-common-sdk
Keywords: nacos,config,configuration,pydantic,settings
Classifier: Development Status :: 4 - Beta
Classifier: Intended Audience :: Developers
Classifier: License :: OSI Approved :: MIT License
Classifier: Operating System :: OS Independent
Classifier: Programming Language :: Python :: 3
Classifier: Programming Language :: Python :: 3.8
Classifier: Programming Language :: Python :: 3.9
Classifier: Programming Language :: Python :: 3.10
Classifier: Programming Language :: Python :: 3.11
Classifier: Programming Language :: Python :: 3.12
Classifier: Topic :: Software Development :: Libraries :: Python Modules
Requires-Python: >=3.8
Requires-Dist: nacos-sdk-python>=3.0.2
Requires-Dist: pydantic>=2.0.0
Requires-Dist: pydantic-settings>=2.0.0
Requires-Dist: httpx>=0.24.0
Provides-Extra: yaml
Requires-Dist: pyyaml>=6.0; extra == "yaml"
Provides-Extra: dev
Requires-Dist: pytest>=7.0.0; extra == "dev"
Requires-Dist: pytest-cov>=4.0.0; extra == "dev"
Requires-Dist: build>=1.0.0; extra == "dev"
Requires-Dist: twine>=4.0.0; extra == "dev"
Dynamic: requires-python
